{
  "skill_id": "ovos-skill-zork2-game.JarbasSkills",
  "source": "https://github.com/JarbasSkills/ovos-skill-zork2-game",
  "license": "Apache-2.0",
  "name": "Zork 2",
  "description": "EXPECT THE UNEXPECTED WHEN YOU TAKE ON ZORK II: THE WIZARD OF FROBOZZ.\nAs you explore the subterranean realm of Zork, you'll continually be confronted with new surprises. Chief among these is the Wizard himself, who'll constantly endeavor to confound you with his capricious powers. But more than that, you'll face a challenge the likes of which you've never experienced before.",
  "examples": [
    "Play zork 2."
  ],
  "tags": [
    "Entertainment",
    "adventure",
    "game",
    "port"
  ],
  "icon": "https://raw.githack.com/FortAwesome/Font-Awesome/master/svgs/solid/door-open.svg",
  "author": "JarbasSkills"
}